eflips/eval/input/__init__.py
eflips/eval/input/prepare.py
eflips/eval/input/route_options.py
eflips/eval/input/routing.py
eflips/eval/input/visualize.py
eflips/eval/output/__init__.py
eflips/eval/output/map_util.py
eflips/eval/output/prepare.py
eflips/eval/output/util.py
eflips/eval/output/visualize.py
eflips/eval/py.typed
eflips_eval-1.9.0.dist-info/METADATA
eflips_eval-1.9.0.dist-info/WHEEL
eflips_eval-1.9.0.dist-info/licenses/LICENSE.md
eflips_eval-1.9.0.dist-info/RECORD
