Metadata-Version: 2.4
Name: eflips-eval
Version: 1.9.0
Summary: 
License-File: LICENSE.md
Author: Ludger Heide
Author-email: ludger.heide@lhtechnologies.de
Requires-Python: >=3.10,<3.14
Classifier: Programming Language :: Python :: 3
Classifier: Programming Language :: Python :: 3.10
Classifier: Programming Language :: Python :: 3.11
Classifier: Programming Language :: Python :: 3.12
Classifier: Programming Language :: Python :: 3.13
Requires-Dist: dash-cytoscape (>=1.0.1,<2.0.0)
Requires-Dist: folium (>=0.17.0,<0.18.0)
Requires-Dist: httpx (>=0.27.0,<0.28.0)
Requires-Dist: matplotlib (>=3.9.0,<4.0.0)
Requires-Dist: pandas (>=2.2.0,<3.0.0)
Requires-Dist: plotly (>=5.19.0,<6.0.0)
Requires-Dist: polyline (>=2.0.0,<3.0.0)
Requires-Dist: seaborn (>=0.13.2,<0.14.0)
Requires-Dist: shapely (>=2.0.5,<3.0.0)
